snakemake_interface_storage_plugins/__init__.py
snakemake_interface_storage_plugins/common.py
snakemake_interface_storage_plugins/io.py
snakemake_interface_storage_plugins/registry/__init__.py
snakemake_interface_storage_plugins/registry/plugin.py
snakemake_interface_storage_plugins/settings.py
snakemake_interface_storage_plugins/storage_object.py
snakemake_interface_storage_plugins/storage_provider.py
snakemake_interface_storage_plugins/tests.py
snakemake_interface_storage_plugins-4.2.3.dist-info/LICENSE
snakemake_interface_storage_plugins-4.2.3.dist-info/METADATA
snakemake_interface_storage_plugins-4.2.3.dist-info/WHEEL
snakemake_interface_storage_plugins-4.2.3.dist-info/RECORD
