Metadata-Version: 2.3
Name: snakemake-interface-storage-plugins
Version: 4.2.3
Summary: This package provides a stable interface for interactions between Snakemake and its storage plugins.
Author: Johannes Koester
Author-email: johannes.koester@uni-due.de
Requires-Python: >=3.11
Classifier: Programming Language :: Python :: 3
Classifier: Programming Language :: Python :: 3.11
Classifier: Programming Language :: Python :: 3.12
Classifier: Programming Language :: Python :: 3.13
Requires-Dist: reretry (>=0.11.8)
Requires-Dist: snakemake-interface-common (>=1.12.0)
Requires-Dist: throttler (>=1.2.2)
Requires-Dist: wrapt (>=1.15.0)
Project-URL: Homepage, https://github.com/snakemake/snakemake-interface-storage-plugins
